codebrief/__init__.py
codebrief/main.py
codebrief/tools/__init__.py
codebrief/tools/bundler.py
codebrief/tools/dependency_lister.py
codebrief/tools/flattener.py
codebrief/tools/git_provider.py
codebrief/tools/tree_generator.py
codebrief/utils/__init__.py
codebrief/utils/config_manager.py
codebrief/utils/ignore_handler.py
codebrief-1.1.0.dist-info/LICENSE
codebrief-1.1.0.dist-info/METADATA
codebrief-1.1.0.dist-info/WHEEL
codebrief-1.1.0.dist-info/entry_points.txt
codebrief-1.1.0.dist-info/RECORD
