Metadata-Version: 2.3
Name: codebrief
Version: 1.1.0
Summary: A CLI toolkit to generate comprehensive project context for LLMs.
License: MIT
Keywords: llm,cli,context,toolkit,documentation
Author: Shourya Maheshwari
Author-email: shorz2905@gmail.com
Requires-Python: >=3.9,<4.0
Classifier: Development Status :: 4 - Beta
Classifier: Intended Audience :: Developers
Classifier: License :: OSI Approved :: MIT License
Classifier: Programming Language :: Python :: 3
Classifier: Programming Language :: Python :: 3.9
Classifier: Programming Language :: Python :: 3.10
Classifier: Programming Language :: Python :: 3.11
Classifier: Programming Language :: Python :: 3.12
Classifier: Programming Language :: Python :: 3.13
Classifier: Topic :: Software Development :: Documentation
Classifier: Topic :: Utilities
Requires-Dist: pathspec (>=0.12.1,<0.13.0)
Requires-Dist: pyperclip (>=1.9.0,<2.0.0)
Requires-Dist: rich (>=13.0.0,<14.0.0)
Requires-Dist: toml (>=0.10.2,<0.11.0)
Requires-Dist: tomli (>=2.0.0,<3.0.0) ; python_version < "3.11"
Requires-Dist: typer (>=0.15.0,<1.0.0)
Project-URL: Documentation, https://shorzinator.github.io/CodeBrief/
Project-URL: Homepage, https://github.com/Shorzinator/CodeBrief
Project-URL: Repository, https://github.com/Shorzinator/CodeBrief
